Metadata-Version: 1.0
Name: goodiepy
Version: 0.0.0
Summary: Some useful methods
Home-page: https://github.com/monzita/goodiepy
Author: Monika Ilieva
Author-email: hidden@hidden.com
License: MIT License
Keywords: goodiepy python3 usefulmethods
Platform: UNKNOWN
